coralillo/__init__.py
coralillo/auth.py
coralillo/core.py
coralillo/datamodel.py
coralillo/errors.py
coralillo/exceptions.py
coralillo/fields.py
coralillo/hashing.py
coralillo/queryset.py
coralillo/utils.py
coralillo/validation.py
coralillo/version.txt
coralillo/lua/__init__.py
coralillo/lua/allow.lua
coralillo/lua/drop.lua
coralillo/lua/is_allowed.lua
coralillo/tests/__init__.py
coralillo/tests/conftest.py
coralillo/tests/datamodel_test.py
coralillo/tests/engine_test.py
coralillo/tests/events_test.py
coralillo/tests/fields_test.py
coralillo/tests/forms_test.py
coralillo/tests/model_test.py
coralillo/tests/models.py
coralillo/tests/permissions_test.py
coralillo/tests/presentation_test.py
coralillo/tests/relations_test.py
coralillo/tests/utils_test.py
coralillo/tests/validation_test.py
coralillo-2.2.1.dist-info/LICENSE.txt
coralillo-2.2.1.dist-info/METADATA
coralillo-2.2.1.dist-info/WHEEL
coralillo-2.2.1.dist-info/top_level.txt
coralillo-2.2.1.dist-info/RECORD
