Metadata-Version: 2.1
Name: coralillo
Version: 2.2.1
Summary: An Object-Redis Mapping
Home-page: https://categulario.gitlab.io/coralillo/
Author: Abraham Toriz Cruz
Author-email: categulario@gmail.com
License: MIT
Keywords: redis database mapper
Platform: UNKNOWN
Classifier: Development Status :: 4 - Beta
Classifier: Intended Audience :: Developers
Classifier: Topic :: Software Development :: Libraries :: Python Modules
Classifier: License :: OSI Approved :: MIT License
Classifier: Programming Language :: Python :: 3
Classifier: Programming Language :: Python :: 3.6
Classifier: Programming Language :: Python :: 3.7
Classifier: Programming Language :: Python :: 3.8
Classifier: Programming Language :: Python :: 3.9
License-File: LICENSE.txt
Requires-Dist: redis (>=3)
Requires-Dist: bcrypt
Provides-Extra: dev
Requires-Dist: check-manifest ; extra == 'dev'
Provides-Extra: test
